osman_hadi/__init__.py
osman_hadi/osman_bio.py
osman_hadi/osman_career.py
osman_hadi/osman_edu.py
osman_hadi/osman_family.py
osman_hadi/osman_initiatives.py
osman_hadi/osman_july.py
osman_hadi/osman_martyrdom.py
osman_hadi/osman_quotes.py
osman_hadi/styles.py
osman_hadi-1.0.12.dist-info/licenses/LICENSE
osman_hadi-1.0.12.dist-info/METADATA
osman_hadi-1.0.12.dist-info/WHEEL
osman_hadi-1.0.12.dist-info/top_level.txt
osman_hadi-1.0.12.dist-info/RECORD
