Metadata-Version: 2.4
Name: osman_hadi
Version: 1.0.12
Summary: A bilingual Python library documenting the life and legacy of Shaheed Osman Bin Hadi.
Home-page: https://github.com/mahadi99900/Osman_Hadi
Author: Mahdi bin iqbal
Author-email: islammdmahadi943@gmail.com
Classifier: Programming Language :: Python :: 3
Classifier: License :: OSI Approved :: MIT License
Classifier: Operating System :: OS Independent
Requires-Python: >=3.6
License-File: LICENSE
Dynamic: author
Dynamic: author-email
Dynamic: classifier
Dynamic: description
Dynamic: description-content-type
Dynamic: home-page
Dynamic: license-file
Dynamic: requires-python
Dynamic: summary
